dq/__init__.py
dq/cache.py
dq/config.py
dq/database.py
dq/dbadmin.py
dq/email.py
dq/entity.py
dq/errors.py
dq/fsutil.py
dq/funcutil.py
dq/logging.py
dq/orm.py
dq/redis.py
dq/retry.py
dq/string.py
dq/util.py
tests/__init__.py
tests/entities.py
tests/models.py
tests/test_cache.py
tests/test_config.py
tests/test_database.py
tests/test_dbadmin.py
tests/test_email.py
tests/test_entity.py
tests/test_errors.py
tests/test_fsutil.py
tests/test_funcutil.py
tests/test_logging.py
tests/test_orm.py
tests/test_redis.py
tests/test_retry.py
tests/test_string.py
tests/test_util.py
dqpy-2.0.6.dist-info/LICENSE
dqpy-2.0.6.dist-info/METADATA
dqpy-2.0.6.dist-info/WHEEL
dqpy-2.0.6.dist-info/entry_points.txt
dqpy-2.0.6.dist-info/top_level.txt
dqpy-2.0.6.dist-info/zip-safe
dqpy-2.0.6.dist-info/RECORD
